[
  {
    "id": 1,
    "title": "АФИША МЕРОПРИЯТИЙ АПРЕЛЬ",
    "description": "В апреле наше кафе становится ещё уютнее - впереди месяц, наполненный вкусом, теплом и яркими событиями для всей семьи!",
    "expiry_date": null,
    "created_at": "Tue Apr 14 2026 12:00:00 GMT+0300 (Moscow Standard Time)",
    "image_url": "https://res.cloudinary.com/dizrpgcxr/image/upload/v1776101560/%D0%90%D1%84%D0%B8%D1%88%D0%B0_%D0%BC%D0%B5%D1%80%D0%BE%D0%BF%D1%80%D0%B8%D1%8F%D1%82%D0%B8%D0%B9_%D0%B0%D0%BF%D1%80%D0%B5%D0%BB%D1%8C_fkqsnw.jpg",
    "link": "https://kukacafe.ru/news/afishaaprel"
  },
  {
    "id": 2,
    "title": "НОВИНКА в «Кука»",
    "description": "Новинка в «Кука» - субботние активности в новом формате!\nЭто отличная возможность провести насыщенный и познавательный день с детьми - квесты, соревнования, творчество и веселье в уютной атмосфере кафе.",
    "expiry_date": null,
    "created_at": "Tue Apr 14 2026 12:00:00 GMT+0300 (Moscow Standard Time)",
    "image_url": "https://res.cloudinary.com/dizrpgcxr/image/upload/v1776109994/%D0%9D%D0%BE%D0%B2%D0%B8%D0%BD%D0%BA%D0%B0_%D0%B2_%D0%9A%D0%A3%D0%9A%D0%90_sdm6iy.jpg",
    "link": "https://kukacafe.ru/news/activnostisubbota"
  },
  {
    "id": 3,
    "title": "Безопасность - это важно.",
    "description": "Мы приглашаем вас на семейный тренинг «Я и чужой взрослый» совместно с экспертами школы «Стоп угроза»",
    "expiry_date": null,
    "created_at": "Tue Apr 14 2026 12:00:00 GMT+0300 (Moscow Standard Time)",
    "image_url": "https://res.cloudinary.com/dizrpgcxr/image/upload/v1776110387/%D0%91%D0%B5%D0%B7%D0%BE%D0%BF%D0%B0%D1%81%D0%BD%D0%BE%D1%81%D1%82%D1%8C_%D1%8D%D1%82%D0%BE_%D0%B2%D0%B0%D0%B6%D0%BD%D0%BE_h8mzni.jpg",
    "link": "https://kukacafe.ru/news/trening-chuzhoy-vzrosliy"
  },
  {
    "id": 4,
    "title": "Художественный\nмастер-класс",
    "description": "Приглашаем вас на уникальный мастер-класс, где каждый сможет раскрыть свой творческий потенциал и создать настоящее произведение искусства!",
    "expiry_date": null,
    "created_at": "Tue Apr 14 2026 12:00:00 GMT+0300 (Moscow Standard Time)",
    "image_url": "https://res.cloudinary.com/dizrpgcxr/image/upload/v1776110566/%D0%A5%D1%83%D0%B4%D0%BE%D0%B6%D0%B5%D1%81%D1%82%D0%B2%D0%B5%D0%BD%D0%BD%D1%8B%D0%B9_%D0%BC%D0%B0%D1%81%D1%82%D0%B5%D1%80-%D0%BA%D0%BB%D0%B0%D1%81%D1%81_p3gpfy.jpg",
    "link": "https://kukacafe.ru/news/mc-hudozhestvenniy-aprel"
  },
  {
    "id": 5,
    "title": "Повтор Новинки в «Кука»!",
    "description": "Рады сообщить, что мы повторяем волшебный интерактивный спектакль для самых маленьких!",
    "expiry_date": null,
    "created_at": "Tue Apr 14 2026 12:00:00 GMT+0300 (Moscow Standard Time)",
    "image_url": "https://res.cloudinary.com/dizrpgcxr/image/upload/v1776114335/%D0%9F%D0%BE%D0%B2%D1%82%D0%BE%D1%80_%D0%BD%D0%BE%D0%B2%D0%B8%D0%BD%D0%BA%D0%B8_b76ml5.jpg",
    "link": "https://kukacafe.ru/news/spectakl-povtor"
  },
  {
    "id": 6,
    "title": "Весенняя сказка в кафе «Кука»",
    "description": "Дорогие друзья! Приглашаем вас окунуться в атмосферу волшебства и насладиться изысканными вкусами на нашем особом весеннем вечере.",
    "expiry_date": null,
    "created_at": "Tue Apr 14 2026 12:00:00 GMT+0300 (Moscow Standard Time)",
    "image_url": "https://res.cloudinary.com/dizrpgcxr/image/upload/v1776114464/%D0%92%D0%B5%D1%81%D0%B5%D0%BD%D0%BD%D1%8F%D1%8F_%D1%81%D0%BA%D0%B0%D0%B7%D0%BA%D0%B0_%D0%B2_%D0%BA%D0%B0%D1%84%D0%B5_fluvij.jpg",
    "link": "https://kukacafe.ru/news/vesennyaja-skazka"
  },
  {
    "id": 35,
    "title": "Старт раннего бронирования выпускных в «Кука»!",
    "description": "Мы рады объявить о запуске раннего бронирования выпускных из детского сада и начальной школы в семейном кафе «Кука»!",
    "expiry_date": "Tue Jan 27 2026 00:00:00 GMT+0300 (Moscow Standard Time)",
    "created_at": "Tue Mar 10 2026 00:00:00 GMT+0300 (Moscow Standard Time)",
    "image_url": "https://res.cloudinary.com/dizrpgcxr/image/upload/v1776118376/%D0%A1%D1%82%D0%B0%D1%80%D1%82_%D1%80%D0%B0%D0%BD%D0%BD%D0%B5%D0%B3%D0%BE_%D0%B1%D1%80%D0%BE%D0%BD%D0%B8%D1%80%D0%BE%D0%B2%D0%B0%D0%BD%D0%B8%D1%8F_%D0%B2%D1%8B%D0%BF%D1%83%D1%81%D0%BA%D0%BD%D1%8B%D1%85_%D0%B2_%D0%9A%D1%83%D0%BA%D0%B0_gfpbtg.jpg",
    "link": "https://kukacafe.ru/vipusknoy"
  },
  {
    "id": 36,
    "title": "НОВИНКА в «Кука»",
    "description": "Приглашаем детей 2–6 лет с родителями в волшебный мир театра! Вместе с добрым режиссёром Иваном Иванычем и его забавными куклами!",
    "expiry_date": "Fri Mar 27 2026 00:00:00 GMT+0300 (Moscow Standard Time)",
    "created_at": "Tue Mar 10 2026 00:00:00 GMT+0300 (Moscow Standard Time)",
    "image_url": "https://res.cloudinary.com/dizrpgcxr/image/upload/v1776118365/%D0%9D%D0%9E%D0%92%D0%98%D0%9D%D0%9A%D0%90_%D0%B2_%D0%9A%D1%83%D0%BA%D0%B0_27_%D0%BC%D0%B0%D1%80%D1%82%D0%B0_hcohxa.jpg",
    "link": "https://kukacafe.ru/news/new-teatr-kukol"
  },
  {
    "id": 37,
    "title": "22 марта - День рождения «Кука»!",
    "description": "Приглашаем отпраздновать первый волшебный юбилей нашего уютного пространства, ставшего за год местом радости, творчества и семейного тепла.",
    "expiry_date": "Sun Mar 22 2026 00:00:00 GMT+0300 (Moscow Standard Time)",
    "created_at": "Tue Mar 10 2026 00:00:00 GMT+0300 (Moscow Standard Time)",
    "image_url": "https://res.cloudinary.com/dizrpgcxr/image/upload/v1776118296/22_%D0%BC%D0%B0%D1%80%D1%82%D0%B0_-_%D0%94%D0%B5%D0%BD%D1%8C_%D1%80%D0%BE%D0%B6%D0%B4%D0%B5%D0%BD%D0%B8%D1%8F_%D0%9A%D1%83%D0%BA%D0%B0_uvgjnj.jpg",
    "link": "https://kukacafe.ru/news/happybirthday-1year"
  },
  {
    "id": 38,
    "title": "Весенняя встреча читательского клуба Алены Катькало",
    "description": "Погрузитесь в атмосферу тёплых встреч, ароматного чая и сладких угощений!",
    "expiry_date": "Sun Mar 15 2026 00:00:00 GMT+0300 (Moscow Standard Time)",
    "created_at": "Tue Mar 10 2026 00:00:00 GMT+0300 (Moscow Standard Time)",
    "image_url": "https://res.cloudinary.com/dizrpgcxr/image/upload/v1776118356/%D0%92%D0%B5%D1%81%D0%B5%D0%BD%D0%BD%D1%8F%D1%8F_%D0%B2%D1%81%D1%82%D1%80%D0%B5%D1%87%D0%B0_%D1%87%D0%B8%D1%82%D0%B0%D1%82%D0%B5%D0%BB%D1%8C%D1%81%D0%BA%D0%BE%D0%B3%D0%BE_%D0%BA%D0%BB%D1%83%D0%B1%D0%B0_%D0%90%D0%BB%D0%B5%D0%BD%D1%8B_%D0%9A%D0%B0%D1%82%D1%8C%D0%BA%D0%B0%D0%BB%D0%BE_mntlqe.jpg",
    "link": "https://kukacafe.ru/news/vesennyayavstrechya"
  },
  {
    "id": 32,
    "title": "АФИША МЕРОПРИЯТИЙ ФЕВРАЛЬ",
    "description": "В феврале наше кафе становится ещё уютнее - впереди месяц, наполненный вкусом, теплом и яркими событиями для всей семьи!",
    "expiry_date": "Fri Feb 13 2026 00:00:00 GMT+0300 (Moscow Standard Time)",
    "created_at": "Mon Feb 23 2026 00:00:00 GMT+0300 (Moscow Standard Time)",
    "image_url": "https://res.cloudinary.com/dizrpgcxr/image/upload/v1776118353/%D0%90%D0%A4%D0%98%D0%A8%D0%90_%D0%9C%D0%95%D0%A0%D0%9E%D0%9F%D0%A0%D0%98%D0%AF%D0%A2%D0%98%D0%99_%D0%A4%D0%95%D0%92%D0%A0%D0%90%D0%9B%D0%AC_uagzjs.jpg",
    "link": "https://kukacafe.ru/news/afishafebruary"
  },
  {
    "id": 33,
    "title": "23 февраля в кафе «Кука»",
    "description": "Праздник силы, доброты и настоящих героев! Приглашаем отметить этот день всей семьёй в атмосфере уюта, веселья и вкусных сюрпризов.",
    "expiry_date": "Fri Feb 13 2026 00:00:00 GMT+0300 (Moscow Standard Time)",
    "created_at": "Mon Feb 23 2026 00:00:00 GMT+0300 (Moscow Standard Time)",
    "image_url": "https://res.cloudinary.com/dizrpgcxr/image/upload/v1776118296/23_%D1%84%D0%B5%D0%B2%D1%80%D0%B0%D0%BB%D1%8F_%D0%B2_%D0%BA%D0%B0%D1%84%D0%B5_%D0%9A%D1%83%D0%BA%D0%B0_mi3pvb.jpg",
    "link": "https://kukacafe.ru/news/paketpred"
  },
  {
    "id": 29,
    "title": "Блинный спэшл в «Кука»!",
    "description": "С 16 по 22 февраля приглашаем вас на вкусный блинный спешл - всю неделю готовим любимые блины с разными начинками, сладкими и сытными!",
    "expiry_date": "Mon Feb 16 2026 00:00:00 GMT+0300 (Moscow Standard Time)",
    "created_at": "Sun Feb 22 2026 00:00:00 GMT+0300 (Moscow Standard Time)",
    "image_url": "https://res.cloudinary.com/dizrpgcxr/image/upload/v1776118354/%D0%91%D0%BB%D0%B8%D0%BD%D0%BD%D1%8B%D0%B9_%D1%81%D0%BF%D1%8D%D1%88%D0%BB_%D0%B2_%D0%9A%D1%83%D0%BA%D0%B0_icb3au.jpg",
    "link": "https://kukacafe.ru/news/maslenitsa2026"
  },
  {
    "id": 31,
    "title": "Масленица в «Кука»!\n20 февраля в 17:00",
    "description": "Большой праздник Масленицы с кулинарным мастер-классом по приготовлению блинного торта, интерактивным спектаклем, катанием на Русской Печи и народными играми.",
    "expiry_date": "Fri Feb 13 2026 00:00:00 GMT+0300 (Moscow Standard Time)",
    "created_at": "Fri Feb 20 2026 00:00:00 GMT+0300 (Moscow Standard Time)",
    "image_url": "https://res.cloudinary.com/dizrpgcxr/image/upload/v1776118363/%D0%9C%D0%B0%D1%81%D0%BB%D0%B5%D0%BD%D0%B8%D1%86%D0%B0_%D0%B2_%D0%9A%D1%83%D0%BA%D0%B0_20_%D1%84%D0%B5%D1%80%D0%B2%D0%B0%D0%BB%D1%8F_vrrpcx.jpg",
    "link": "https://kukacafe.ru/news/maslenitsaspecial"
  },
  {
    "id": 34,
    "title": "День Святого Валентина в «Кука»",
    "description": "Приглашаем вас 14 февраля окунуться в атмосферу любви, радости и сладких эмоций!",
    "expiry_date": "Tue Jan 27 2026 00:00:00 GMT+0300 (Moscow Standard Time)",
    "created_at": "Sat Feb 14 2026 00:00:00 GMT+0300 (Moscow Standard Time)",
    "image_url": "https://res.cloudinary.com/dizrpgcxr/image/upload/v1776118359/%D0%94%D0%B5%D0%BD%D1%8C_%D0%A1%D0%B2%D1%8F%D1%82%D0%BE%D0%B3%D0%BE_%D0%92%D0%B0%D0%BB%D0%B5%D0%BD%D1%82%D0%B8%D0%BD%D0%B0_%D0%B2_%D0%9A%D1%83%D0%BA%D0%B0_y7x01w.jpg",
    "link": "https://kukacafe.ru/news/svvalentinsday"
  },
  {
    "id": 30,
    "title": "Творческий февраль в семейном кафе «Кука»",
    "description": "С 4 по 13 февраля мы проводим серию детских и семейных мастер‑классов: рисуем, лепим, создаём подарки и уютный декор своими руками.",
    "expiry_date": "Fri Feb 13 2026 00:00:00 GMT+0300 (Moscow Standard Time)",
    "created_at": "Wed Feb 04 2026 00:00:00 GMT+0300 (Moscow Standard Time)",
    "image_url": "https://res.cloudinary.com/dizrpgcxr/image/upload/v1776118379/%D0%A2%D0%B2%D0%BE%D1%80%D1%87%D0%B5%D1%81%D0%BA%D0%B8%D0%B9_%D1%84%D0%B5%D0%B2%D1%80%D0%B0%D0%BB%D1%8C_%D0%B2_%D1%81%D0%B5%D0%BC%D0%B5%D0%B9%D0%BD%D0%BE%D0%BC_%D0%BA%D0%B0%D1%84%D0%B5_%D0%9A%D1%83%D0%BA%D0%B0_x1lt8e.jpg",
    "link": "https://kukacafe.ru/news/tvfestival"
  },
  {
    "id": 25,
    "title": "Первая встреча читательского клуба Алены Катькало в новом году!",
    "description": "На этой встрече мы вместе окунёмся в захватывающий мир книги «Денискины рассказы».",
    "expiry_date": "Sun Feb 01 2026 00:00:00 GMT+0300 (Moscow Standard Time)",
    "created_at": "Sat Jan 10 2026 00:00:00 GMT+0300 (Moscow Standard Time)",
    "image_url": "https://res.cloudinary.com/dizrpgcxr/image/upload/v1776118373/%D0%9F%D0%B5%D1%80%D0%B2%D0%B0%D1%8F_%D0%B2%D1%81%D1%82%D1%80%D0%B5%D1%87%D0%B0_%D1%87%D0%B8%D1%82%D0%B0%D1%82%D0%B5%D0%BB%D1%8C%D1%81%D0%BA%D0%BE%D0%B3%D0%BE_%D0%BA%D0%BB%D1%83%D0%B1%D0%B0_%D0%90%D0%BB%D0%B5%D0%BD%D1%8B_%D0%9A%D0%B0%D1%82%D1%8C%D0%BA%D0%B0%D0%BB%D0%BE_%D0%B2_%D0%BD%D0%BE%D0%B2%D0%BE%D0%BC_%D0%B3%D0%BE%D0%B4%D1%83_hbrwo3.jpg",
    "link": "https://kukacafe.ru/news/deniskinirasskazy"
  },
  {
    "id": 26,
    "title": "Художественный мастер-класс",
    "description": "Мы с радостью приглашаем вас на новую встречу в этом году.\nВас ждёт тёплый вечер творчества и вдохновения.",
    "expiry_date": "Fri Jan 23 2026 00:00:00 GMT+0300 (Moscow Standard Time)",
    "created_at": "Sat Jan 10 2026 00:00:00 GMT+0300 (Moscow Standard Time)",
    "image_url": "https://res.cloudinary.com/dizrpgcxr/image/upload/v1776118603/%D0%A5%D1%83%D0%B4%D0%BE%D0%B6%D0%B5%D1%81%D1%82%D0%B2%D0%B5%D0%BD%D0%BD%D1%8B%D0%B9_%D0%BC%D0%B0%D1%81%D1%82%D0%B5%D1%80-%D0%BA%D0%BB%D0%B0%D1%81%D1%81_23_%D1%8F%D0%BD%D0%B2%D0%B0%D1%80%D1%8F_und7po.jpg",
    "link": "https://kukacafe.ru/news/hudmc"
  },
  {
    "id": 27,
    "title": "Пакетное предложение «Близкий круг»",
    "description": "Пригласите свой близкий круг в уютный уголок «Кука» и позвольте нам позаботиться обо всем!",
    "expiry_date": "Mon Jan 26 2026 00:00:00 GMT+0300 (Moscow Standard Time)",
    "created_at": "Sat Jan 10 2026 00:00:00 GMT+0300 (Moscow Standard Time)",
    "image_url": "https://res.cloudinary.com/dizrpgcxr/image/upload/v1776118371/%D0%9F%D0%B0%D0%BA%D0%B5%D1%82%D0%BD%D0%BE%D0%B5_%D0%BF%D1%80%D0%B5%D0%B4%D0%BB%D0%BE%D0%B6%D0%B5%D0%BD%D0%B8%D0%B5_%D0%91%D0%BB%D0%B8%D0%B7%D0%BA%D0%B8%D0%B9_%D0%BA%D1%80%D1%83%D0%B3_p0agql.jpg",
    "link": "https://kukacafe.ru/news/paketpred"
  },
  {
    "id": 28,
    "title": "Успейте до закрытия!",
    "description": "Будни с бонусами в игровой зоне с понедельника по четверг.",
    "expiry_date": "Tue Jan 27 2026 00:00:00 GMT+0300 (Moscow Standard Time)",
    "created_at": "Sat Jan 10 2026 00:00:00 GMT+0300 (Moscow Standard Time)",
    "image_url": "https://res.cloudinary.com/dizrpgcxr/image/upload/v1776118409/%D0%A3%D1%81%D0%BF%D0%B5%D0%B9%D1%82%D0%B5_%D0%B4%D0%BE_%D0%B7%D0%B0%D0%BA%D1%80%D1%8B%D1%82%D0%B8%D1%8F_qu79zc.jpg",
    "link": "https://kukacafe.ru/news/bonusbudni"
  },
  {
    "id": 24,
    "title": "«Кука» — это уютное семейное кафе",
    "description": "Итог: игровая зона - для детей, но вкусная еда и уют - для всех! \n«Кука» - комфортно каждому",
    "expiry_date": "Wed Dec 31 2025 00:00:00 GMT+0300 (Moscow Standard Time)",
    "created_at": "Wed Dec 31 2025 00:00:00 GMT+0300 (Moscow Standard Time)",
    "image_url": "https://res.cloudinary.com/dizrpgcxr/image/upload/v1776118361/%D0%9A%D1%83%D0%BA%D0%B0_%D1%8D%D1%82%D0%BE_%D1%83%D1%8E%D1%82%D0%BD%D0%BE%D0%B5_%D1%81%D0%B5%D0%BC%D0%B5%D0%B9%D0%BD%D0%BE%D0%B5_%D0%BA%D0%B0%D1%84%D0%B5_k4wmge.jpg",
    "link": "https://kukacafe.ru/news/question"
  },
  {
    "id": 22,
    "title": "Анонс предзаказа вареников",
    "description": "Мы рады предложить вам два вкуса настоящих домашних вареников\nПрием предзаказов открыт!\nЗабронируйте свою порцию заранее.",
    "expiry_date": "Wed Dec 31 2025 00:00:00 GMT+0300 (Moscow Standard Time)",
    "created_at": "Tue Dec 30 2025 00:00:00 GMT+0300 (Moscow Standard Time)",
    "image_url": "https://res.cloudinary.com/dizrpgcxr/image/upload/v1776118296/%D0%90%D0%BD%D0%BE%D0%BD%D1%81_%D0%BF%D1%80%D0%B5%D0%B4%D0%B7%D0%B0%D0%BA%D0%B0%D0%B7%D0%BE%D0%B2_%D0%B2%D0%B0%D1%80%D0%B5%D0%BD%D0%B8%D0%BA%D0%BE%D0%B2_afn3jp.jpg",
    "link": "https://kukacafe.ru/news/vareniki"
  },
  {
    "id": 23,
    "title": "Приглашение в семейное кафе «Кука»",
    "description": "Мы с радостью представляем обновлённое меню завтраков - уютное, вкусное и по-настоящему долгожданное. Оно обязательно понравится как взрослым, так и детям.",
    "expiry_date": "Wed Dec 31 2025 00:00:00 GMT+0300 (Moscow Standard Time)",
    "created_at": "Tue Dec 30 2025 00:00:00 GMT+0300 (Moscow Standard Time)",
    "image_url": "https://res.cloudinary.com/dizrpgcxr/image/upload/v1776118374/%D0%9F%D1%80%D0%B8%D0%B3%D0%BB%D0%B0%D1%88%D0%B5%D0%BD%D0%B8%D0%B5_%D0%B2_%D1%81%D0%B5%D0%BC%D0%B5%D0%B9%D0%BD%D0%BE%D0%B5_%D0%BA%D0%B0%D1%84%D0%B5_%D0%9A%D1%83%D0%BA%D0%B0_q52uxw.jpg",
    "link": "https://kukacafe.ru/news/zavtraki"
  },
  {
    "id": 21,
    "title": "Важно! Режим работы в праздничные дни",
    "description": "С 31 декабря по 11 января\n1 января — выходной день\nВ игровых зонах действует тариф выходного дня.",
    "expiry_date": "Wed Dec 31 2025 00:00:00 GMT+0300 (Moscow Standard Time)",
    "created_at": "Mon Dec 29 2025 00:00:00 GMT+0300 (Moscow Standard Time)",
    "image_url": "https://res.cloudinary.com/dizrpgcxr/image/upload/v1776118355/%D0%92%D0%B0%D0%B6%D0%BD%D0%BE_%D0%A0%D0%B5%D0%B6%D0%B8%D0%BC_%D1%80%D0%B0%D0%B1%D0%BE%D1%82%D1%8B_%D0%B2_%D0%BF%D1%80%D0%B0%D0%B7%D0%B4%D0%BD%D0%B8%D1%87%D0%BD%D1%8B%D0%B5_%D0%B4%D0%BD%D0%B8_cuzhxh.jpg",
    "link": "https://kukacafe.ru/news/nyprice"
  },
  {
    "id": 18,
    "title": "Новогодние праздники в «Кука»",
    "description": "С 2 по 11 января 2026 года приглашаем вас на волшебную встречу с Дедушкой Морозом!",
    "expiry_date": "Wed Dec 31 2025 00:00:00 GMT+0300 (Moscow Standard Time)",
    "created_at": "Sun Dec 28 2025 00:00:00 GMT+0300 (Moscow Standard Time)",
    "image_url": "https://res.cloudinary.com/dizrpgcxr/image/upload/v1776118368/%D0%9D%D0%BE%D0%B2%D0%BE%D0%B3%D0%BE%D0%B4%D0%BD%D0%B8%D0%B5_%D0%BF%D1%80%D0%B0%D0%B7%D0%B4%D0%BD%D0%B8%D0%BA%D0%B8_%D0%B2_%D0%9A%D1%83%D0%BA%D0%B0_cdnpii.jpg",
    "link": "https://kukacafe.ru/news/nycelebrations"
  },
  {
    "id": 19,
    "title": "Розыгрыш призов в семейном кафе «Кука»",
    "description": "С 1 по 31 декабря 2025 года в кафе проходит акция «Письмо Деду Морозу». Все письма, отправленные через Кука-почту автоматически участвуют в розыгрыше призов!",
    "expiry_date": "Wed Dec 31 2025 00:00:00 GMT+0300 (Moscow Standard Time)",
    "created_at": "Sun Dec 28 2025 00:00:00 GMT+0300 (Moscow Standard Time)",
    "image_url": "https://res.cloudinary.com/dizrpgcxr/image/upload/v1776118375/%D0%A0%D0%BE%D0%B7%D1%8B%D0%B3%D1%80%D1%8B%D1%88_%D0%BF%D1%80%D0%B8%D0%B7%D0%BE%D0%B2_%D0%B2_%D1%81%D0%B5%D0%BC%D0%B5%D0%B9%D0%BD%D0%BE%D0%BC_%D0%BA%D0%B0%D1%84%D0%B5_%D0%BA%D1%83%D0%BA%D0%B0_rewndh.jpg",
    "link": "https://kukacafe.ru/news/prise"
  },
  {
    "id": 20,
    "title": "Афиша новогодних активностей в Кука",
    "description": "2–11 января с 09:00 до 21:00\nПриглашаем провести зимние каникулы весело и с пользой!",
    "expiry_date": "Wed Dec 31 2025 00:00:00 GMT+0300 (Moscow Standard Time)",
    "created_at": "Sun Dec 28 2025 00:00:00 GMT+0300 (Moscow Standard Time)",
    "image_url": "https://res.cloudinary.com/dizrpgcxr/image/upload/v1776118354/%D0%90%D1%84%D0%B8%D1%88%D0%B0_%D0%BD%D0%BE%D0%B2%D0%BE%D0%B3%D0%BE%D0%B4%D0%BD%D0%B8%D1%85_%D0%B0%D0%BA%D1%82%D0%B8%D0%B2%D0%BD%D0%BE%D1%81%D1%82%D0%B5%D0%B9_%D0%B2_%D0%9A%D1%83%D0%BA%D0%B0_lupkau.jpg",
    "link": "https://kukacafe.ru/news/afishany"
  },
  {
    "id": 17,
    "title": "Детский клуб в семейном кафе «Кука»",
    "description": "Вам нужно уделить время себе, но не с кем оставить ребенка? Приходите в детский клуб семейного кафе «Кука»!",
    "expiry_date": "Wed Dec 31 2025 00:00:00 GMT+0300 (Moscow Standard Time)",
    "created_at": "Sat Dec 27 2025 00:00:00 GMT+0300 (Moscow Standard Time)",
    "image_url": "https://res.cloudinary.com/dizrpgcxr/image/upload/v1776118360/%D0%94%D0%B5%D1%82%D1%81%D0%BA%D0%B8%D0%B9_%D0%BA%D0%BB%D1%83%D0%B1_%D0%B2_%D1%81%D0%B5%D0%BC%D0%B5%D0%B9%D0%BD%D0%BE%D0%BC_%D0%BA%D0%B0%D1%84%D0%B5_%D0%9A%D1%83%D0%BA%D0%B0_u9y8xb.jpg",
    "link": "https://kukacafe.ru/news/detskiyclub"
  },
  {
    "id": 15,
    "title": "Мастер-класс «Безумное чаепитие в Кука»",
    "description": "Приглашаем детей от 3 лет (вместе с мамой или самостоятельно) окунуться в атмосферу «Алисы в стране чудес» со Шляпником",
    "expiry_date": "Wed Dec 31 2025 00:00:00 GMT+0300 (Moscow Standard Time)",
    "created_at": "Fri Dec 26 2025 00:00:00 GMT+0300 (Moscow Standard Time)",
    "image_url": "https://res.cloudinary.com/dizrpgcxr/image/upload/v1776118364/%D0%9C%D0%B0%D1%81%D1%82%D0%B5%D1%80-%D0%BA%D0%BB%D0%B0%D1%81%D1%81_%D0%B1%D0%B5%D0%B7%D1%83%D0%BC%D0%BD%D0%BE%D0%B5_%D1%87%D0%B0%D0%B5%D0%BF%D0%B8%D1%82%D0%B8%D0%B5_ejb11a.jpg",
    "link": "https://kukacafe.ru/news/mcalice"
  },
  {
    "id": 16,
    "title": "Счастливые часы в игровой зоне Кука",
    "description": "Это отличная возможность совместить завтрак, обед с отличным отдыхом, зарядиться энергией и весело провести время в уютной атмосфере, избежав вечерней суеты.",
    "expiry_date": "Wed Dec 31 2025 00:00:00 GMT+0300 (Moscow Standard Time)",
    "created_at": "Fri Dec 26 2025 00:00:00 GMT+0300 (Moscow Standard Time)",
    "image_url": "https://res.cloudinary.com/dizrpgcxr/image/upload/v1776118377/%D0%A1%D1%87%D0%B0%D1%81%D1%82%D0%BB%D0%B8%D0%B2%D1%8B%D0%B5_%D1%87%D0%B0%D1%81%D1%8B_%D0%B2_%D0%B8%D0%B3%D1%80%D0%BE%D0%B2%D0%BE%D0%B9_%D0%B7%D0%BE%D0%BD%D0%B5_%D0%9A%D1%83%D0%BA%D0%B0_m2i2hq.jpg",
    "link": "https://kukacafe.ru/news/happytime"
  },
  {
    "id": 12,
    "title": "Милые мамы,\nс Днём матери!",
    "description": "Вы невероятные, и мы благодарны, что вы выбираете «Кука» для своих тёплых семейных моментов.",
    "expiry_date": "Wed Dec 31 2025 00:00:00 GMT+0300 (Moscow Standard Time)",
    "created_at": "Thu Dec 25 2025 12:00:00 GMT+0300 (Moscow Standard Time)",
    "image_url": "https://res.cloudinary.com/dizrpgcxr/image/upload/v1776118358/%D0%94%D0%B5%D0%BD%D1%8C_%D0%BC%D0%B0%D1%82%D0%B5%D1%80%D0%B8_neagns.jpg",
    "link": "https://kukacafe.ru/news/motherday"
  },
  {
    "id": 13,
    "title": "Окунитесь в волшебство зимы!",
    "description": "Пора насладиться уникальным зимним меню в Кука! \nНаши талантливые повара создали неповторимые блюда, которые впечатляют не только вкусом, но и изысканной подачей.",
    "expiry_date": "Wed Dec 31 2025 00:00:00 GMT+0300 (Moscow Standard Time)",
    "created_at": "Thu Dec 25 2025 12:00:00 GMT+0300 (Moscow Standard Time)",
    "image_url": "https://res.cloudinary.com/dizrpgcxr/image/upload/v1776118357/%D0%92%D0%BE%D0%BB%D1%88%D0%B5%D0%B1%D1%81%D1%82%D0%B2%D0%BE_%D0%B7%D0%B8%D0%BC%D1%8B_fkfwo1.jpg",
    "link": "https://kukacafe.ru/news/wintermenu"
  },
  {
    "id": 14,
    "title": "Новогодние\nмастер-классы для детей",
    "description": "12 декабря приглашаем вас и вашего ребёнка на увлекательный творческий мастер-класс",
    "expiry_date": "Wed Dec 31 2025 00:00:00 GMT+0300 (Moscow Standard Time)",
    "created_at": "Thu Dec 25 2025 12:00:00 GMT+0300 (Moscow Standard Time)",
    "image_url": "https://res.cloudinary.com/dizrpgcxr/image/upload/v1776118367/%D0%9D%D0%BE%D0%B2%D0%BE%D0%B3%D0%BE%D0%B4%D0%BD%D0%B8%D0%B5_%D0%BC%D0%B0%D1%81%D1%82%D0%B5%D1%80-%D0%BA%D0%BB%D0%B0%D1%81%D1%81%D1%8B_ecmkjq.jpg",
    "link": "https://kukacafe.ru/news/newyearmc"
  },
  {
    "id": 10,
    "title": "Новогодние чудеса в «Кука» для самых маленьких 2-5 лет",
    "description": "Для малышей мы приготовили добрый, теплый праздник 18 и 25 декабря с 11:30 до 13:00",
    "expiry_date": "Wed Dec 31 2025 00:00:00 GMT+0300 (Moscow Standard Time)",
    "created_at": "Thu Dec 18 2025 12:00:00 GMT+0300 (Moscow Standard Time)",
    "image_url": "https://res.cloudinary.com/dizrpgcxr/image/upload/v1776118370/%D0%9D%D0%BE%D0%B2%D1%8B%D0%B9_%D0%B3%D0%BE%D0%B4_18_%D0%B8_25_%D0%B4%D0%B5%D0%BA%D0%B0%D0%B1%D1%80%D1%8F_e8whyv.jpg",
    "link": "https://kukacafe.ru/news/newyear6-11"
  },
  {
    "id": 11,
    "title": "Миссия Новый год начинается в «Кука» для детей 6-11 лет",
    "description": "Для ребят постарше мы подготовили незабываемое праздничное путешествие 18 и 25 декабря с 18:00 до 19:30",
    "expiry_date": "Wed Dec 31 2025 00:00:00 GMT+0300 (Moscow Standard Time)",
    "created_at": "Thu Dec 18 2025 12:00:00 GMT+0300 (Moscow Standard Time)",
    "image_url": "https://res.cloudinary.com/dizrpgcxr/image/upload/v1776118369/%D0%9D%D0%BE%D0%B2%D0%BE%D0%B3%D0%BE%D0%B4%D0%BD%D0%B8%D0%B9_%D1%83%D1%82%D1%80%D0%B5%D0%BD%D0%BD%D0%B8%D0%BA_6-11_exrbxf.jpg",
    "link": "https://kukacafe.ru/news/newyear2-5"
  },
  {
    "id": 9,
    "title": "Творческая мастерская по выходным с 14:00 до 19:00",
    "description": "Лепим, рисуем, мастерим, фантазируем.",
    "expiry_date": "Wed Dec 31 2025 00:00:00 GMT+0300 (Moscow Standard Time)",
    "created_at": "Mon Dec 01 2025 12:00:00 GMT+0300 (Moscow Standard Time)",
    "image_url": "https://res.cloudinary.com/dizrpgcxr/image/upload/v1776118378/%D0%A2%D0%B2%D0%BE%D1%80%D1%87%D0%B5%D1%81%D0%BA%D0%B0%D1%8F_%D0%BC%D0%B0%D1%81%D1%82%D0%B5%D1%80%D1%81%D0%BA%D0%B0%D1%8F_%D0%BF%D0%BE_%D0%B2%D1%8B%D1%85%D0%BE%D0%B4%D0%BD%D1%8B%D0%BC_pylx3f.jpg",
    "link": "https://kukacafe.ru/news/tmaster"
  },
  {
    "id": 7,
    "title": "Художественный мастер-класс от Александра Долондуцкого",
    "description": "Fri Nov 27 2026 17:00:00 GMT+0300 (Moscow Standard Time)",
    "expiry_date": "Wed Dec 31 2025 00:00:00 GMT+0300 (Moscow Standard Time)",
    "created_at": "Thu Nov 27 2025 12:00:00 GMT+0300 (Moscow Standard Time)",
    "image_url": "https://res.cloudinary.com/dizrpgcxr/image/upload/v1776118764/%D0%A5%D1%83%D0%B4%D0%BE%D0%B6%D0%B5%D1%81%D1%82%D0%B2%D0%B5%D0%BD%D0%BD%D1%8B%D0%B9_%D0%BC%D0%B0%D1%81%D1%82%D0%B5%D1%80-%D0%BA%D0%BB%D0%B0%D1%81%D1%81_%D0%BE%D1%82_%D0%90%D0%BB%D0%B5%D0%BA%D1%81%D0%B0%D0%BD%D0%B4%D1%80%D0%B0_%D0%94%D0%BE%D0%BB%D0%BE%D0%BD%D0%B4%D1%83%D1%86%D0%BA%D0%BE%D0%B3%D0%BE_27_%D0%BD%D0%BE%D1%8F%D0%B1%D1%80%D1%8F_dwoskt.jpg",
    "link": ""
  },
  {
    "id": 8,
    "title": "Новинка! Читательский клуб Алены Катькало в кафе «Кука»",
    "description": "Мы открываем новый сезон. Впереди много ярких событий!",
    "expiry_date": "Wed Dec 31 2025 00:00:00 GMT+0300 (Moscow Standard Time)",
    "created_at": "Sat Nov 15 2025 12:00:00 GMT+0300 (Moscow Standard Time)",
    "image_url": "https://res.cloudinary.com/dizrpgcxr/image/upload/v1776118367/%D0%9D%D0%BE%D0%B2%D0%B8%D0%BD%D0%BA%D0%B0_%D0%A7%D0%B8%D1%82%D0%B0%D1%82%D0%B5%D0%BB%D1%8C%D1%81%D0%BA%D0%B8%D0%B9_%D0%BA%D0%BB%D1%83%D0%B1_%D0%90%D0%BB%D0%B5%D0%BD%D1%8B_%D0%9A%D0%B0%D1%82%D1%8C%D0%BA%D0%B0%D0%BB%D0%BE_%D0%B2_%D0%BA%D0%B0%D1%84%D0%B5_%D0%9A%D1%83%D0%BA%D0%B0_tjba7n.jpg",
    "link": "https://kukacafe.ru/rclub"
  },
  {
    "id": 39,
    "title": "",
    "description": "",
    "expiry_date": null,
    "created_at": null,
    "image_url": "",
    "link": ""
  },
  {
    "id": 40,
    "title": "",
    "description": "",
    "expiry_date": null,
    "created_at": null,
    "image_url": "",
    "link": ""
  },
  {
    "id": 41,
    "title": "",
    "description": "",
    "expiry_date": null,
    "created_at": null,
    "image_url": "",
    "link": ""
  }
]